curseforge_cli/__init__.py
curseforge_cli/cli.py
curseforge_cli/core/__init__.py
curseforge_cli/core/api.py
curseforge_cli/core/game.py
curseforge_cli/core/model.py
curseforge_cli/core/utils.py
curseforge_cli-0.1.1.dist-info/METADATA
curseforge_cli-0.1.1.dist-info/WHEEL
curseforge_cli-0.1.1.dist-info/entry_points.txt
curseforge_cli-0.1.1.dist-info/top_level.txt
curseforge_cli-0.1.1.dist-info/RECORD
