Metadata-Version: 2.1
Name: curseforge-cli
Version: 0.1.1
Summary: Command line addon manager for World of Warcraft, TES: Online, Minecraft and more
Home-page: https://github.com/mtalimanchuk/curseforge-cli
Author: Maxim Talimanchuk
Author-email: mtalimanchuk@gmail.com
License: UNKNOWN
Platform: UNKNOWN
Requires-Python: >=3.7,<4
Requires-Dist: pydantic (<2.0.0,>=1.8.2)
Requires-Dist: requests (<3.0.0,>=2.26.0)
Requires-Dist: setuptools (==58.0.4)
